[{"cmd": "add ./test", "app": "/home/ubuntu/FogArmX/test", "timestamp": 1655631042.9971664, "fogbrain": 0.038761138916015625, "Placement": {"application": "test", "ToAdd": [["redis", "node1-garr-ct1"], ["web", "node1-garr-ct1"]], "ToRemove": [], "ToMigrate": []}, "ToAdd": 2, "avg-to_add": 14.300309538841248, "actuate": 28.600813627243042, "total_time": 32.84409499168396}, {"cmd": "add ./test", "app": "/home/ubuntu/FogArmX/test", "timestamp": 1655631077.3984857, "fogbrain": 0.038132429122924805, "Placement": {"application": "test", "ToAdd": [], "ToRemove": [], "ToMigrate": [["redis", "node1-garr-ct1", "node2-garr-ct1"], ["web", "node1-garr-ct1", "node2-garr-ct1"]]}, "ToMigrate": 2, "avg-to_migrate": 9.708892703056335, "actuate": 38.0707471370697, "total_time": 42.16892147064209}, {"cmd": "add ./test", "app": "/home/ubuntu/FogArmX/test", "timestamp": 1655631121.437515, "fogbrain": 0.03844809532165527, "Placement": {"application": "test", "ToAdd": [], "ToRemove": [["redis", "node2-garr-ct1"]], "ToMigrate": [["web", "node2-garr-ct1", "node1-garr-ct1"]]}, "ToMigrate": 1, "avg-to_migrate": 16.031481742858887, "ToRemove": 1, "avg-to_remove": 0.11919140815734863, "actuate": 16.150762796401978, "total_time": 19.238454341888428}, {"cmd": "add ./test", "app": "/home/ubuntu/FogArmX/test", "timestamp": 1655631141.8009615, "fogbrain": 0.04075431823730469, "Placement": {"application": "test", "ToAdd": [["redis", "node1-garr-ct1"]], "ToRemove": [], "ToMigrate": []}, "ToAdd": 1, "avg-to_add": 12.831047296524048, "actuate": 12.831124544143677, "total_time": 17.44226336479187}, {"cmd": "add ./test", "app": "/home/ubuntu/FogArmX/test", "timestamp": 1655631160.9889877, "fogbrain": 0.04183197021484375, "Placement": {"application": "test", "ToAdd": [], "ToRemove": [], "ToMigrate": [["redis", "node1-garr-ct1", "node3-garr-ct1"], ["web", "node1-garr-ct1", "node2-garr-ct1"]]}, "ToMigrate": 2, "avg-to_migrate": 8.051742672920227, "actuate": 34.317397117614746, "total_time": 38.737404584884644}, {"cmd": "add ./test", "app": "/home/ubuntu/FogArmX/test", "timestamp": 1655631201.3675437, "fogbrain": 0.04393124580383301, "Placement": {"application": "test", "ToAdd": [], "ToRemove": [], "ToMigrate": [["web", "node2-garr-ct1", "node1-garr-ct1"]]}, "ToMigrate": 1, "avg-to_migrate": 15.900840282440186, "actuate": 15.900920629501343, "total_time": 19.90674877166748}, {"cmd": "add ./test", "app": "/home/ubuntu/FogArmX/test", "timestamp": 1655631222.780535, "fogbrain": 0.04222893714904785, "Placement": {"application": "test", "ToAdd": [], "ToRemove": [], "ToMigrate": []}, "actuate": 8.320808410644531e-05, "total_time": 4.126302719116211}, {"cmd": "add ./test", "app": "/home/ubuntu/FogArmX/test", "timestamp": 1655631228.3549695, "fogbrain": 0.03847670555114746, "Placement": {"application": "test", "ToAdd": [], "ToRemove": [], "ToMigrate": [["redis", "node3-garr-ct1", "node1-garr-ct1"]]}, "ToMigrate": 1, "avg-to_migrate": 15.277612447738647, "actuate": 15.277729988098145, "total_time": 19.400399446487427}, {"cmd": "add ./test", "app": "/home/ubuntu/FogArmX/test", "timestamp": 1655631249.2603467, "fogbrain": 0.0383296012878418, "Placement": {"application": "test", "ToAdd": [], "ToRemove": [], "ToMigrate": []}, "actuate": 2.6464462280273438e-05, "total_time": 3.8686635494232178}, {"cmd": "add /home/ubuntu/FogArmX/GARR/apps/docker-swarm-demo-0/", "app": "/home/ubuntu/FogArmX/GARR/apps/docker-swarm-demo-0", "timestamp": 1655632075.7963254, "fogbrain": 0.0800786018371582, "Placement": {"application": "docker-swarm-demo-0", "ToAdd": [["api-gateway", "node0-garr-pa1"], ["webapp", "node0-garr-pa1"], ["invoices_db", "node0-garr-pa1"], ["products_db", "node0-garr-pa1"], ["products", "node0-garr-pa1"], ["customers_db", "node0-garr-pa1"]], "ToRemove": [], "ToMigrate": []}, "ToAdd": 6, "avg-to_add": 21.99011508623759, "actuate": 131.94076204299927, "total_time": 148.80926322937012}, {"cmd": "add /home/ubuntu/FogArmX/GARR/apps/docker-swarm-demo-1/", "app": "/home/ubuntu/FogArmX/GARR/apps/docker-swarm-demo-1", "timestamp": 1655632230.500488, "fogbrain": 0.07565093040466309, "Placement": {"application": "docker-swarm-demo-1", "ToAdd": [["webapp", "node3-garr-to1"], ["invoices_db", "node3-garr-to1"], ["invoices", "node3-garr-to1"], ["products_db", "node3-garr-to1"], ["products", "node3-garr-to1"], ["customers_db", "node3-garr-to1"], ["customers", "node3-garr-to1"]], "ToRemove": [], "ToMigrate": []}, "ToAdd": 7, "avg-to_add": 18.93075524057661, "actuate": 132.51536011695862, "total_time": 164.14761233329773}, {"cmd": "add /home/ubuntu/FogArmX/GARR/apps/docker-swarm-demo-2/", "app": "/home/ubuntu/FogArmX/GARR/apps/docker-swarm-demo-2", "timestamp": 1655632400.8325799, "fogbrain": 0.07509875297546387, "Placement": {"application": "docker-swarm-demo-2", "ToAdd": [["api-gateway", "node12-garr-to1"], ["webapp", "node12-garr-to1"], ["invoices_db", "node12-garr-to1"], ["products_db", "node12-garr-to1"], ["products", "node12-garr-to1"], ["customers_db", "node12-garr-to1"], ["customers", "node12-garr-to1"]], "ToRemove": [], "ToMigrate": []}, "ToAdd": 7, "avg-to_add": 20.597236939838954, "actuate": 144.18073868751526, "total_time": 198.33986163139343}, {"cmd": "add /home/ubuntu/FogArmX/GARR/apps/docker-swarm-demo-3/", "app": "/home/ubuntu/FogArmX/GARR/apps/docker-swarm-demo-3", "timestamp": 1655632605.6443791, "fogbrain": 0.0881814956665039, "Placement": {"application": "docker-swarm-demo-3", "ToAdd": [["api-gateway", "node12-garr-to1"], ["invoices_db", "node12-garr-to1"], ["invoices", "node12-garr-to1"], ["products_db", "node12-garr-to1"], ["products", "node12-garr-to1"], ["customers_db", "node12-garr-to1"], ["customers", "node12-garr-to1"]], "ToRemove": [], "ToMigrate": []}, "ToAdd": 7, "avg-to_add": 15.127990313938685, "actuate": 105.89599871635437, "total_time": 138.01245617866516}, {"cmd": "add /home/ubuntu/FogArmX/GARR/apps/docker-swarm-demo-4/", "app": "/home/ubuntu/FogArmX/GARR/apps/docker-swarm-demo-4", "timestamp": 1655632749.5065887, "fogbrain": 0.06548285484313965, "Placement": {"application": "docker-swarm-demo-4", "ToAdd": [["webapp", "node14-garr-ct1"], ["invoices_db", "node14-garr-ct1"], ["invoices", "node14-garr-ct1"], ["products_db", "node14-garr-ct1"], ["products", "node14-garr-ct1"], ["customers_db", "node14-garr-ct1"], ["customers", "node14-garr-ct1"]], "ToRemove": [], "ToMigrate": []}, "ToAdd": 7, "avg-to_add": 26.046300377164567, "actuate": 182.32423090934753, "total_time": 226.93429279327393}, {"cmd": "add /home/ubuntu/FogArmX/GARR/apps/docker-swarm-demo-5/", "app": "/home/ubuntu/FogArmX/GARR/apps/docker-swarm-demo-5", "timestamp": 1655632982.329691, "fogbrain": 0.06914305686950684, "Placement": {"application": "docker-swarm-demo-5", "ToAdd": [["api-gateway", "node2-garr-to1"], ["invoices_db", "node2-garr-to1"], ["invoices", "node2-garr-to1"], ["products_db", "node2-garr-to1"], ["products", "node2-garr-to1"], ["customers_db", "node2-garr-to1"], ["customers", "node2-garr-to1"]], "ToRemove": [], "ToMigrate": []}, "ToAdd": 7, "avg-to_add": 22.92949448313032, "actuate": 160.50654125213623, "total_time": 208.31885600090027}, {"cmd": "add /home/ubuntu/FogArmX/GARR/apps/docker-swarm-demo-6/", "app": "/home/ubuntu/FogArmX/GARR/apps/docker-swarm-demo-6", "timestamp": 1655633196.498352, "fogbrain": 0.0652456283569336, "Placement": {"application": "docker-swarm-demo-6", "ToAdd": [["api-gateway", "node12-garr-pa1"], ["webapp", "node12-garr-pa1"], ["invoices_db", "node12-garr-pa1"], ["invoices", "node12-garr-pa1"], ["products_db", "node12-garr-pa1"], ["products", "node12-garr-pa1"], ["customers_db", "node12-garr-pa1"], ["customers", "node12-garr-pa1"]], "ToRemove": [], "ToMigrate": []}, "ToAdd": 8, "avg-to_add": 22.493081659078598, "actuate": 179.94475865364075, "total_time": 318.13287353515625}, {"cmd": "add /home/ubuntu/FogArmX/GARR/apps/docker-swarm-demo-7/", "app": "/home/ubuntu/FogArmX/GARR/apps/docker-swarm-demo-7", "timestamp": 1655633520.8255649, "fogbrain": 0.0821843147277832, "Placement": {"application": "docker-swarm-demo-7", "ToAdd": [["api-gateway", "node8-garr-to1"], ["webapp", "node8-garr-to1"], ["invoices_db", "node8-garr-to1"], ["invoices", "node8-garr-to1"], ["products_db", "node8-garr-to1"], ["products", "node8-garr-to1"], ["customers_db", "node8-garr-to1"], ["customers", "node8-garr-to1"]], "ToRemove": [], "ToMigrate": []}, "ToAdd": 8, "avg-to_add": 19.206734478473663, "actuate": 153.6540105342865, "total_time": 313.6799545288086}, {"cmd": "add /home/ubuntu/FogArmX/GARR/apps/docker-swarm-demo-8/", "app": "/home/ubuntu/FogArmX/GARR/apps/docker-swarm-demo-8", "timestamp": 1655633842.1845813, "fogbrain": 0.1863417625427246, "Placement": {"application": "docker-swarm-demo-8", "ToAdd": [["api-gateway", "node8-garr-to1"], ["invoices_db", "node8-garr-to1"], ["invoices", "node8-garr-to1"], ["products_db", "node8-garr-to1"], ["products", "node8-garr-to1"], ["customers_db", "node8-garr-to1"]], "ToRemove": [], "ToMigrate": []}, "ToAdd": 6, "avg-to_add": 23.428812980651855, "actuate": 140.57293677330017, "total_time": 260.4770703315735}, {"cmd": "add /home/ubuntu/FogArmX/GARR/apps/docker-swarm-demo-9/", "app": "/home/ubuntu/FogArmX/GARR/apps/docker-swarm-demo-9", "timestamp": 1655634108.6411994, "fogbrain": 0.07341217994689941, "Placement": {"application": "docker-swarm-demo-9", "ToAdd": [["api-gateway", "node13-garr-ct1"], ["webapp", "node13-garr-ct1"], ["invoices_db", "node13-garr-ct1"], ["invoices", "node13-garr-ct1"], ["products_db", "node13-garr-ct1"], ["products", "node13-garr-ct1"], ["customers_db", "node13-garr-ct1"], ["customers", "node13-garr-ct1"]], "ToRemove": [], "ToMigrate": []}, "ToAdd": 8, "avg-to_add": 24.95786765217781, "actuate": 199.6630129814148, "total_time": 397.9004783630371}, {"cmd": "add /home/ubuntu/FogArmX/GARR/apps/docker-swarm-demo-10/", "app": "/home/ubuntu/FogArmX/GARR/apps/docker-swarm-demo-10", "timestamp": 1655634514.2469938, "fogbrain": 0.2113511562347412, "Placement": {"application": "docker-swarm-demo-10", "ToAdd": [["api-gateway", "node13-garr-ct1"], ["webapp", "node13-garr-ct1"], ["invoices_db", "node13-garr-ct1"], ["invoices", "node13-garr-ct1"], ["products_db", "node13-garr-ct1"], ["customers_db", "node13-garr-ct1"], ["customers", "node13-garr-ct1"]], "ToRemove": [], "ToMigrate": []}, "ToAdd": 7, "avg-to_add": 24.4491468838283, "actuate": 171.14411425590515, "total_time": 320.87463879585266}, {"cmd": "add /home/ubuntu/FogArmX/GARR/apps/docker-swarm-demo-11/", "app": "/home/ubuntu/FogArmX/GARR/apps/docker-swarm-demo-11", "timestamp": 1655634841.358891, "fogbrain": 0.13909530639648438, "Placement": {"application": "docker-swarm-demo-11", "ToAdd": [["webapp", "node18-garr-pa1"], ["invoices_db", "node18-garr-pa1"], ["products_db", "node18-garr-pa1"], ["products", "node18-garr-pa1"], ["customers_db", "node18-garr-pa1"], ["customers", "node18-garr-pa1"]], "ToRemove": [], "ToMigrate": []}, "ToAdd": 6, "avg-to_add": 21.81375805536906, "actuate": 130.88261032104492, "total_time": 369.19126749038696}, {"cmd": "add /home/ubuntu/FogArmX/GARR/apps/docker-swarm-demo-12/", "app": "/home/ubuntu/FogArmX/GARR/apps/docker-swarm-demo-12", "timestamp": 1655635218.3491802, "fogbrain": 0.19988083839416504, "Placement": {"application": "docker-swarm-demo-12", "ToAdd": [["api-gateway", "node18-garr-pa1"], ["webapp", "node18-garr-pa1"], ["invoices_db", "node18-garr-pa1"], ["invoices", "node18-garr-pa1"], ["products_db", "node18-garr-pa1"], ["products", "node18-garr-pa1"], ["customers_db", "node18-garr-pa1"], ["customers", "node18-garr-pa1"]], "ToRemove": [], "ToMigrate": []}, "ToAdd": 8, "avg-to_add": 26.301929712295532, "actuate": 210.4154999256134, "total_time": 487.79034090042114}, {"cmd": "add /home/ubuntu/FogArmX/GARR/apps/docker-swarm-demo-13/", "app": "/home/ubuntu/FogArmX/GARR/apps/docker-swarm-demo-13", "timestamp": 1655635713.4610066, "fogbrain": 0.18254399299621582, "Placement": {"application": "docker-swarm-demo-13", "ToAdd": [["api-gateway", "node18-garr-pa1"], ["webapp", "node18-garr-pa1"], ["invoices_db", "node18-garr-pa1"], ["invoices", "node18-garr-pa1"], ["products_db", "node18-garr-pa1"], ["products", "node18-garr-pa1"], ["customers_db", "node18-garr-pa1"], ["customers", "node18-garr-pa1"]], "ToRemove": [], "ToMigrate": []}, "ToAdd": 8, "avg-to_add": 19.923595517873764, "actuate": 159.38885188102722, "total_time": 430.31861567497253}, {"cmd": "add /home/ubuntu/FogArmX/GARR/apps/docker-swarm-demo-14/", "app": "/home/ubuntu/FogArmX/GARR/apps/docker-swarm-demo-14", "timestamp": 1655636150.9126973, "fogbrain": 0.17755508422851562, "Placement": {"application": "docker-swarm-demo-14", "ToAdd": [["webapp", "node11-garr-ct1"], ["invoices_db", "node11-garr-ct1"], ["products_db", "node11-garr-ct1"], ["products", "node11-garr-ct1"], ["customers_db", "node11-garr-ct1"], ["customers", "node11-garr-ct1"]], "ToRemove": [], "ToMigrate": []}, "ToAdd": 6, "avg-to_add": 37.04118164380392, "actuate": 222.24714016914368, "total_time": 531.2581832408905}, {"cmd": "add /home/ubuntu/FogArmX/GARR/apps/docker-swarm-demo-15/", "app": "/home/ubuntu/FogArmX/GARR/apps/docker-swarm-demo-15", "timestamp": 1655636689.4043548, "fogbrain": 0.19780397415161133, "Placement": {"application": "docker-swarm-demo-15", "ToAdd": [["api-gateway", "node11-garr-ct1"], ["webapp", "node11-garr-ct1"], ["invoices_db", "node11-garr-ct1"], ["products_db", "node11-garr-ct1"], ["products", "node11-garr-ct1"], ["customers_db", "node11-garr-ct1"], ["customers", "node11-garr-ct1"]], "ToRemove": [], "ToMigrate": []}, "ToAdd": 7, "avg-to_add": 29.24219686644418, "actuate": 204.6954424381256, "total_time": 508.01972341537476}, {"cmd": "add /home/ubuntu/FogArmX/GARR/apps/docker-swarm-demo-16/", "app": "/home/ubuntu/FogArmX/GARR/apps/docker-swarm-demo-16", "timestamp": 1655637203.3485298, "fogbrain": 0.06587767601013184, "Placement": {"application": "docker-swarm-demo-16", "ToAdd": [["api-gateway", "node10-garr-to1"], ["webapp", "node10-garr-to1"], ["invoices_db", "node10-garr-to1"], ["invoices", "node10-garr-to1"], ["products_db", "node10-garr-to1"], ["products", "node10-garr-to1"], ["customers_db", "node10-garr-to1"], ["customers", "node10-garr-to1"]], "ToRemove": [], "ToMigrate": []}, "ToAdd": 8, "avg-to_add": 22.757318645715714, "actuate": 182.058611869812, "total_time": 556.8859553337097}, {"cmd": "add /home/ubuntu/FogArmX/GARR/apps/docker-swarm-demo-17/", "app": "/home/ubuntu/FogArmX/GARR/apps/docker-swarm-demo-17", "timestamp": 1655637768.1217675, "fogbrain": 0.23003840446472168, "Placement": {"application": "docker-swarm-demo-17", "ToAdd": [["api-gateway", "node10-garr-to1"], ["webapp", "node10-garr-to1"], ["invoices_db", "node10-garr-to1"], ["products_db", "node10-garr-to1"], ["products", "node10-garr-to1"], ["customers_db", "node10-garr-to1"], ["customers", "node10-garr-to1"]], "ToRemove": [], "ToMigrate": []}, "ToAdd": 7, "avg-to_add": 39.31909659930638, "actuate": 275.2337455749512, "total_time": 632.8017349243164}, {"cmd": "add /home/ubuntu/FogArmX/GARR/apps/docker-swarm-demo-18/", "app": "/home/ubuntu/FogArmX/GARR/apps/docker-swarm-demo-18", "timestamp": 1655638408.4056673, "fogbrain": 0.22668671607971191, "Placement": {"application": "docker-swarm-demo-18", "ToAdd": [["webapp", "node10-garr-to1"], ["invoices_db", "node10-garr-to1"], ["invoices", "node10-garr-to1"], ["products_db", "node10-garr-to1"], ["products", "node10-garr-to1"], ["customers_db", "node10-garr-to1"], ["customers", "node10-garr-to1"]], "ToRemove": [], "ToMigrate": []}, "ToAdd": 7, "avg-to_add": 36.76766208239964, "actuate": 257.3737235069275, "total_time": 687.5450720787048}, {"cmd": "add /home/ubuntu/FogArmX/GARR/apps/docker-swarm-demo-19/", "app": "/home/ubuntu/FogArmX/GARR/apps/docker-swarm-demo-19", "timestamp": 1655639103.7277718, "fogbrain": 0.1971449851989746, "Placement": {"application": "docker-swarm-demo-19", "ToAdd": [["api-gateway", "node10-garr-to1"], ["webapp", "node10-garr-to1"], ["invoices_db", "node10-garr-to1"], ["invoices", "node10-garr-to1"], ["products_db", "node10-garr-to1"], ["products", "node10-garr-to1"], ["customers_db", "node10-garr-to1"], ["customers", "node10-garr-to1"]], "ToRemove": [], "ToMigrate": []}, "ToAdd": 8, "avg-to_add": 33.690787464380264, "actuate": 269.5263752937317, "total_time": 640.8105463981628}, {"cmd": "add /home/ubuntu/FogArmX/GARR/apps/docker-swarm-demo-20/", "app": "/home/ubuntu/FogArmX/GARR/apps/docker-swarm-demo-20", "timestamp": 1655639752.1592197, "fogbrain": 0.19527935981750488, "Placement": {"application": "docker-swarm-demo-20", "ToAdd": [["api-gateway", "node19-garr-ct1"], ["webapp", "node19-garr-ct1"], ["invoices_db", "node19-garr-ct1"], ["products_db", "node19-garr-ct1"], ["products", "node19-garr-ct1"], ["customers_db", "node19-garr-ct1"], ["customers", "node19-garr-ct1"]], "ToRemove": [], "ToMigrate": []}, "ToAdd": 7, "avg-to_add": 42.55827133996146, "actuate": 297.90796518325806, "total_time": 756.7649521827698}, {"cmd": "add /home/ubuntu/FogArmX/GARR/apps/docker-swarm-demo-21/", "app": "/home/ubuntu/FogArmX/GARR/apps/docker-swarm-demo-21", "timestamp": 1655640516.1832714, "fogbrain": 0.22571802139282227, "Placement": {"application": "docker-swarm-demo-21", "ToAdd": [["api-gateway", "node19-garr-ct1"], ["webapp", "node19-garr-ct1"], ["invoices_db", "node19-garr-ct1"], ["invoices", "node19-garr-ct1"], ["products_db", "node19-garr-ct1"], ["products", "node19-garr-ct1"], ["customers_db", "node19-garr-ct1"], ["customers", "node19-garr-ct1"]], "ToRemove": [], "ToMigrate": []}, "ToAdd": 8, "avg-to_add": 34.97766473889351, "actuate": 279.82139563560486, "total_time": 770.5962879657745}, {"cmd": "add /home/ubuntu/FogArmX/GARR/apps/docker-swarm-demo-22/", "app": "/home/ubuntu/FogArmX/GARR/apps/docker-swarm-demo-22", "timestamp": 1655641294.1856582, "fogbrain": 0.20648622512817383, "Placement": {"application": "docker-swarm-demo-22", "ToAdd": [["api-gateway", "node19-garr-ct1"], ["webapp", "node19-garr-ct1"], ["invoices_db", "node19-garr-ct1"], ["invoices", "node19-garr-ct1"], ["products_db", "node19-garr-ct1"], ["products", "node19-garr-ct1"], ["customers_db", "node19-garr-ct1"]], "ToRemove": [], "ToMigrate": []}, "ToAdd": 7, "avg-to_add": 36.3486373765128, "actuate": 254.4405426979065, "total_time": 740.7949142456055}, {"cmd": "add /home/ubuntu/FogArmX/GARR/apps/docker-swarm-demo-23/", "app": "/home/ubuntu/FogArmX/GARR/apps/docker-swarm-demo-23", "timestamp": 1655642042.4902885, "fogbrain": 0.17795944213867188, "Placement": {"application": "docker-swarm-demo-23", "ToAdd": [["webapp", "node19-garr-ct1"], ["invoices_db", "node19-garr-ct1"], ["invoices", "node19-garr-ct1"], ["products_db", "node19-garr-ct1"], ["products", "node19-garr-ct1"], ["customers_db", "node19-garr-ct1"]], "ToRemove": [], "ToMigrate": []}, "ToAdd": 6, "avg-to_add": 42.03484992186228, "actuate": 252.20915365219116, "total_time": 571.9315207004547}, {"cmd": "add /home/ubuntu/FogArmX/GARR/apps/docker-swarm-demo-24/", "app": "/home/ubuntu/FogArmX/GARR/apps/docker-swarm-demo-24", "timestamp": 1655642622.0045507, "fogbrain": 0.26493310928344727, "Placement": {"application": "docker-swarm-demo-24", "ToAdd": [["api-gateway", "node4-garr-ct1"], ["invoices_db", "node4-garr-ct1"], ["invoices", "node4-garr-ct1"], ["products_db", "node4-garr-ct1"], ["products", "node4-garr-ct1"], ["customers_db", "node4-garr-ct1"], ["customers", "node4-garr-ct1"]], "ToRemove": [], "ToMigrate": []}, "ToAdd": 7, "avg-to_add": 42.70223076002939, "actuate": 298.9156742095947, "total_time": 817.2586090564728}, {"cmd": "add /home/ubuntu/FogArmX/GARR/apps/docker-swarm-demo-25/", "app": "/home/ubuntu/FogArmX/GARR/apps/docker-swarm-demo-25", "timestamp": 1655643446.7682824, "fogbrain": 0.20174384117126465, "Placement": {"application": "docker-swarm-demo-25", "ToAdd": [["api-gateway", "node4-garr-ct1"], ["invoices_db", "node4-garr-ct1"], ["products_db", "node4-garr-ct1"], ["products", "node4-garr-ct1"], ["customers_db", "node4-garr-ct1"], ["customers", "node4-garr-ct1"]], "ToRemove": [], "ToMigrate": []}, "ToAdd": 6, "avg-to_add": 45.25352442264557, "actuate": 271.5212411880493, "total_time": 856.5047526359558}, {"cmd": "add /home/ubuntu/FogArmX/GARR/apps/docker-swarm-demo-26/", "app": "/home/ubuntu/FogArmX/GARR/apps/docker-swarm-demo-26", "timestamp": 1655644310.8285236, "fogbrain": 0.19059157371520996, "Placement": {"application": "docker-swarm-demo-26", "ToAdd": [["webapp", "node4-garr-ct1"], ["invoices_db", "node4-garr-ct1"], ["invoices", "node4-garr-ct1"], ["products_db", "node4-garr-ct1"], ["products", "node4-garr-ct1"], ["customers_db", "node4-garr-ct1"], ["customers", "node4-garr-ct1"]], "ToRemove": [], "ToMigrate": []}, "ToAdd": 7, "avg-to_add": 42.98139704976763, "actuate": 300.8698501586914, "total_time": 872.4625351428986}, {"cmd": "add /home/ubuntu/FogArmX/GARR/apps/docker-swarm-demo-27/", "app": "/home/ubuntu/FogArmX/GARR/apps/docker-swarm-demo-27", "timestamp": 1655645190.4891589, "fogbrain": 0.19828104972839355, "Placement": {"application": "docker-swarm-demo-27", "ToAdd": [["api-gateway", "node4-garr-ct1"], ["webapp", "node4-garr-ct1"], ["invoices_db", "node4-garr-ct1"], ["invoices", "node4-garr-ct1"], ["products_db", "node4-garr-ct1"], ["products", "node4-garr-ct1"], ["customers_db", "node4-garr-ct1"], ["customers", "node4-garr-ct1"]], "ToRemove": [], "ToMigrate": []}, "ToAdd": 8, "avg-to_add": 37.76589444279671, "actuate": 302.1272175312042, "total_time": 873.9003093242645}, {"cmd": "add /home/ubuntu/FogArmX/GARR/apps/docker-swarm-demo-28/", "app": "/home/ubuntu/FogArmX/GARR/apps/docker-swarm-demo-28", "timestamp": 1655646071.8078673, "fogbrain": 0.16886210441589355, "Placement": {"application": "docker-swarm-demo-28", "ToAdd": [["api-gateway", "node4-garr-ct1"], ["webapp", "node4-garr-ct1"], ["invoices_db", "node4-garr-ct1"], ["invoices", "node4-garr-ct1"], ["products_db", "node4-garr-ct1"], ["products", "node4-garr-ct1"], ["customers_db", "node4-garr-ct1"]], "ToRemove": [], "ToMigrate": []}, "ToAdd": 7, "avg-to_add": 44.810474838529316, "actuate": 313.6733875274658, "total_time": 732.2616515159607}, {"cmd": "add /home/ubuntu/FogArmX/GARR/apps/docker-swarm-demo-29/", "app": "/home/ubuntu/FogArmX/GARR/apps/docker-swarm-demo-29", "timestamp": 1655646811.6220746, "fogbrain": 0.14155817031860352, "Placement": {"application": "docker-swarm-demo-29", "ToAdd": [["api-gateway", "node13-garr-pa1"], ["webapp", "node13-garr-pa1"], ["invoices_db", "node13-garr-pa1"], ["invoices", "node13-garr-pa1"], ["products_db", "node13-garr-pa1"], ["products", "node13-garr-pa1"], ["customers_db", "node13-garr-pa1"], ["customers", "node13-garr-pa1"]], "ToRemove": [], "ToMigrate": []}, "ToAdd": 8, "avg-to_add": 46.65330931544304, "actuate": 373.2265245914459, "total_time": 1009.8419892787933}, {"cmd": "add /home/ubuntu/FogArmX/GARR/apps/docker-swarm-demo-30/", "app": "/home/ubuntu/FogArmX/GARR/apps/docker-swarm-demo-30", "timestamp": 1655647829.0175412, "fogbrain": 0.19769740104675293, "Placement": {"application": "docker-swarm-demo-30", "ToAdd": [["invoices_db", "node13-garr-pa1"], ["invoices", "node13-garr-pa1"], ["products_db", "node13-garr-pa1"], ["products", "node13-garr-pa1"], ["customers_db", "node13-garr-pa1"], ["customers", "node13-garr-pa1"]], "ToRemove": [], "ToMigrate": []}, "ToAdd": 6, "avg-to_add": 49.54166853427887, "actuate": 297.2500870227814, "total_time": 916.5679225921631}, {"cmd": "add /home/ubuntu/FogArmX/GARR/apps/docker-swarm-demo-31/", "app": "/home/ubuntu/FogArmX/GARR/apps/docker-swarm-demo-31", "timestamp": 1655648752.868726, "fogbrain": 0.18936371803283691, "Placement": {"application": "docker-swarm-demo-31", "ToAdd": [["api-gateway", "node13-garr-pa1"], ["invoices_db", "node13-garr-pa1"], ["invoices", "node13-garr-pa1"], ["products_db", "node13-garr-pa1"], ["products", "node13-garr-pa1"], ["customers_db", "node13-garr-pa1"], ["customers", "node13-garr-pa1"]], "ToRemove": [], "ToMigrate": []}, "ToAdd": 7, "avg-to_add": 42.72307893208095, "actuate": 299.06160950660706, "total_time": 945.9567399024963}, {"cmd": "add /home/ubuntu/FogArmX/GARR/apps/docker-swarm-demo-32/", "app": "/home/ubuntu/FogArmX/GARR/apps/docker-swarm-demo-32", "timestamp": 1655649706.1582322, "fogbrain": 0.20797443389892578, "Placement": {"application": "docker-swarm-demo-32", "ToAdd": [["api-gateway", "node13-garr-pa1"], ["invoices_db", "node13-garr-pa1"], ["invoices", "node13-garr-pa1"], ["products_db", "node13-garr-pa1"], ["products", "node13-garr-pa1"], ["customers_db", "node13-garr-pa1"], ["customers", "node13-garr-pa1"]], "ToRemove": [], "ToMigrate": []}, "ToAdd": 7, "avg-to_add": 49.52656200953892, "actuate": 346.68599939346313, "total_time": 1028.248975276947}, {"cmd": "add /home/ubuntu/FogArmX/GARR/apps/docker-swarm-demo-33/", "app": "/home/ubuntu/FogArmX/GARR/apps/docker-swarm-demo-33", "timestamp": 1655650742.1944747, "fogbrain": 0.19976091384887695, "Placement": {"application": "docker-swarm-demo-33", "ToAdd": [["api-gateway", "node13-garr-pa1"], ["webapp", "node13-garr-pa1"], ["invoices_db", "node13-garr-pa1"], ["invoices", "node13-garr-pa1"], ["products_db", "node13-garr-pa1"], ["products", "node13-garr-pa1"], ["customers_db", "node13-garr-pa1"], ["customers", "node13-garr-pa1"]], "ToRemove": [], "ToMigrate": []}, "ToAdd": 8, "avg-to_add": 46.83114382624626, "actuate": 374.6492235660553, "total_time": 1070.2006661891937}, {"cmd": "add /home/ubuntu/FogArmX/GARR/apps/docker-swarm-demo-34/", "app": "/home/ubuntu/FogArmX/GARR/apps/docker-swarm-demo-34", "timestamp": 1655651820.2958515, "fogbrain": 0.19387292861938477, "Placement": {"application": "docker-swarm-demo-34", "ToAdd": [["api-gateway", "node13-garr-pa1"], ["webapp", "node13-garr-pa1"], ["invoices_db", "node13-garr-pa1"], ["invoices", "node13-garr-pa1"], ["products_db", "node13-garr-pa1"], ["products", "node13-garr-pa1"], ["customers_db", "node13-garr-pa1"], ["customers", "node13-garr-pa1"]], "ToRemove": [], "ToMigrate": []}, "ToAdd": 8, "avg-to_add": 46.16536393761635, "actuate": 369.3229913711548, "total_time": 1030.9444544315338}, {"cmd": "add /home/ubuntu/FogArmX/GARR/apps/docker-swarm-demo-35/", "app": "/home/ubuntu/FogArmX/GARR/apps/docker-swarm-demo-35", "timestamp": 1655652857.1961937, "fogbrain": 0.06962323188781738, "Placement": {"application": "docker-swarm-demo-35", "ToAdd": [["api-gateway", "node19-garr-to1"], ["webapp", "node19-garr-to1"], ["invoices_db", "node19-garr-to1"], ["invoices", "node19-garr-to1"], ["products_db", "node19-garr-to1"], ["products", "node19-garr-to1"], ["customers_db", "node19-garr-to1"], ["customers", "node19-garr-to1"]], "ToRemove": [], "ToMigrate": []}, "ToAdd": 8, "avg-to_add": 41.967484802007675, "actuate": 335.73995208740234, "total_time": 1052.1292977333069}, {"cmd": "add /home/ubuntu/FogArmX/GARR/apps/docker-swarm-demo-36/", "app": "/home/ubuntu/FogArmX/GARR/apps/docker-swarm-demo-36", "timestamp": 1655653916.418902, "fogbrain": 0.18277740478515625, "Placement": {"application": "docker-swarm-demo-36", "ToAdd": [["api-gateway", "node19-garr-to1"], ["invoices_db", "node19-garr-to1"], ["invoices", "node19-garr-to1"], ["products_db", "node19-garr-to1"], ["products", "node19-garr-to1"], ["customers_db", "node19-garr-to1"], ["customers", "node19-garr-to1"]], "ToRemove": [], "ToMigrate": []}, "ToAdd": 7, "avg-to_add": 47.773499488830566, "actuate": 334.4145612716675, "total_time": 1099.632740497589}, {"cmd": "add /home/ubuntu/FogArmX/GARR/apps/docker-swarm-demo-37/", "app": "/home/ubuntu/FogArmX/GARR/apps/docker-swarm-demo-37", "timestamp": 1655655023.2608483, "fogbrain": 0.16239094734191895, "Placement": {"application": "docker-swarm-demo-37", "ToAdd": [["api-gateway", "node19-garr-to1"], ["webapp", "node19-garr-to1"], ["invoices_db", "node19-garr-to1"], ["invoices", "node19-garr-to1"], ["products_db", "node19-garr-to1"], ["products", "node19-garr-to1"], ["customers_db", "node19-garr-to1"], ["customers", "node19-garr-to1"]], "ToRemove": [], "ToMigrate": []}, "ToAdd": 8, "avg-to_add": 46.12218329310417, "actuate": 368.9775245189667, "total_time": 1149.1704061031342}, {"cmd": "add /home/ubuntu/FogArmX/GARR/apps/docker-swarm-demo-38/", "app": "/home/ubuntu/FogArmX/GARR/apps/docker-swarm-demo-38", "timestamp": 1655656179.837125, "fogbrain": 0.1971895694732666, "Placement": {"application": "docker-swarm-demo-38", "ToAdd": [["api-gateway", "node19-garr-to1"], ["webapp", "node19-garr-to1"], ["invoices_db", "node19-garr-to1"], ["invoices", "node19-garr-to1"], ["products_db", "node19-garr-to1"], ["products", "node19-garr-to1"], ["customers_db", "node19-garr-to1"], ["customers", "node19-garr-to1"]], "ToRemove": [], "ToMigrate": []}, "ToAdd": 8, "avg-to_add": 49.275273859500885, "actuate": 394.2022488117218, "total_time": 1184.1360862255096}, {"cmd": "add /home/ubuntu/FogArmX/GARR/apps/docker-swarm-demo-39/", "app": "/home/ubuntu/FogArmX/GARR/apps/docker-swarm-demo-39", "timestamp": 1655657371.2810183, "fogbrain": 0.14373993873596191, "Placement": {"application": "docker-swarm-demo-39", "ToAdd": [["api-gateway", "node19-garr-to1"], ["webapp", "node19-garr-to1"], ["invoices_db", "node19-garr-to1"], ["invoices", "node19-garr-to1"], ["products_db", "node19-garr-to1"], ["customers_db", "node19-garr-to1"], ["customers", "node19-garr-to1"]], "ToRemove": [], "ToMigrate": []}, "ToAdd": 7, "avg-to_add": 52.20450145857675, "actuate": 365.4315710067749, "total_time": 1101.3910868167877}, {"cmd": "add /home/ubuntu/FogArmX/GARR/apps/docker-swarm-demo-40/", "app": "/home/ubuntu/FogArmX/GARR/apps/docker-swarm-demo-40", "timestamp": 1655658480.1612475, "fogbrain": 0.1027536392211914, "Placement": {"application": "docker-swarm-demo-40", "ToAdd": [["api-gateway", "node19-garr-to1"], ["webapp", "node19-garr-to1"], ["invoices_db", "node19-garr-to1"], ["invoices", "node19-garr-to1"], ["products_db", "node19-garr-to1"], ["products", "node19-garr-to1"], ["customers_db", "node19-garr-to1"], ["customers", "node19-garr-to1"]], "ToRemove": [], "ToMigrate": []}, "ToAdd": 8, "avg-to_add": 45.52809178829193, "actuate": 364.2247884273529, "total_time": 1156.461130142212}, {"cmd": "add /home/ubuntu/FogArmX/GARR/apps/docker-swarm-demo-41/", "app": "/home/ubuntu/FogArmX/GARR/apps/docker-swarm-demo-41", "timestamp": 1655659643.7692382, "fogbrain": 0.17702317237854004, "Placement": {"application": "docker-swarm-demo-41", "ToAdd": [["api-gateway", "node19-garr-to1"], ["webapp", "node19-garr-to1"], ["invoices_db", "node19-garr-to1"], ["invoices", "node19-garr-to1"], ["products_db", "node19-garr-to1"], ["products", "node19-garr-to1"], ["customers_db", "node19-garr-to1"], ["customers", "node19-garr-to1"]], "ToRemove": [], "ToMigrate": []}, "ToAdd": 8, "avg-to_add": 50.31041160225868, "actuate": 402.4833490848541, "total_time": 1279.4749438762665}, {"cmd": "add /home/ubuntu/FogArmX/GARR/apps/docker-swarm-demo-42/", "app": "/home/ubuntu/FogArmX/GARR/apps/docker-swarm-demo-42", "timestamp": 1655660930.4549875, "fogbrain": 0.17222023010253906, "Placement": {"application": "docker-swarm-demo-42", "ToAdd": [["api-gateway", "node19-garr-to1"], ["webapp", "node19-garr-to1"], ["invoices_db", "node19-garr-to1"], ["products_db", "node19-garr-to1"], ["products", "node19-garr-to1"], ["customers_db", "node19-garr-to1"], ["customers", "node19-garr-to1"]], "ToRemove": [], "ToMigrate": []}, "ToAdd": 7, "avg-to_add": 66.0819239956992, "actuate": 462.57351994514465, "total_time": 1175.2345607280731}, {"cmd": "add /home/ubuntu/FogArmX/GARR/apps/docker-swarm-demo-43/", "app": "/home/ubuntu/FogArmX/GARR/apps/docker-swarm-demo-43", "timestamp": 1655662113.3137147, "fogbrain": 0.20482802391052246, "Placement": {"application": "docker-swarm-demo-43", "ToAdd": [["api-gateway", "node19-garr-pa1"], ["webapp", "node19-garr-pa1"], ["invoices_db", "node19-garr-pa1"], ["invoices", "node19-garr-pa1"], ["products_db", "node19-garr-pa1"], ["products", "node19-garr-pa1"], ["customers_db", "node19-garr-pa1"], ["customers", "node19-garr-pa1"]], "ToRemove": [], "ToMigrate": []}, "ToAdd": 8, "avg-to_add": 70.5845656991005, "actuate": 564.6766023635864, "total_time": 1528.3749792575836}, {"cmd": "add /home/ubuntu/FogArmX/GARR/apps/docker-swarm-demo-44/", "app": "/home/ubuntu/FogArmX/GARR/apps/docker-swarm-demo-44", "timestamp": 1655663649.2260234, "fogbrain": 0.19530963897705078, "Placement": {"application": "docker-swarm-demo-44", "ToAdd": [["invoices_db", "node19-garr-pa1"], ["invoices", "node19-garr-pa1"], ["products_db", "node19-garr-pa1"], ["products", "node19-garr-pa1"], ["customers_db", "node19-garr-pa1"], ["customers", "node19-garr-pa1"]], "ToRemove": [], "ToMigrate": []}, "ToAdd": 6, "avg-to_add": 82.54454978307088, "actuate": 495.26738691329956, "total_time": 1443.1970613002777}, {"cmd": "add /home/ubuntu/FogArmX/GARR/apps/docker-swarm-demo-45/", "app": "/home/ubuntu/FogArmX/GARR/apps/docker-swarm-demo-45", "timestamp": 1655665100.0109422, "fogbrain": 0.1794285774230957, "Placement": {"application": "docker-swarm-demo-45", "ToAdd": [["api-gateway", "node19-garr-pa1"], ["invoices_db", "node19-garr-pa1"], ["products_db", "node19-garr-pa1"], ["products", "node19-garr-pa1"], ["customers_db", "node19-garr-pa1"], ["customers", "node19-garr-pa1"]], "ToRemove": [], "ToMigrate": []}, "ToAdd": 6, "avg-to_add": 65.89498333136241, "actuate": 395.37003350257874, "total_time": 1293.1105961799622}, {"cmd": "add /home/ubuntu/FogArmX/GARR/apps/docker-swarm-demo-46/", "app": "/home/ubuntu/FogArmX/GARR/apps/docker-swarm-demo-46", "timestamp": 1655666400.615159, "fogbrain": 0.20763945579528809, "Placement": {"application": "docker-swarm-demo-46", "ToAdd": [["api-gateway", "node19-garr-pa1"], ["webapp", "node19-garr-pa1"], ["invoices_db", "node19-garr-pa1"], ["invoices", "node19-garr-pa1"], ["products_db", "node19-garr-pa1"], ["customers_db", "node19-garr-pa1"], ["customers", "node19-garr-pa1"]], "ToRemove": [], "ToMigrate": []}, "ToAdd": 7, "avg-to_add": 59.43575235775539, "actuate": 416.0503420829773, "total_time": 1336.2530624866486}, {"cmd": "add /home/ubuntu/FogArmX/GARR/apps/docker-swarm-demo-47/", "app": "/home/ubuntu/FogArmX/GARR/apps/docker-swarm-demo-47", "timestamp": 1655667744.4729185, "fogbrain": 0.25362372398376465, "Placement": {"application": "docker-swarm-demo-47", "ToAdd": [["api-gateway", "node19-garr-pa1"], ["webapp", "node19-garr-pa1"], ["invoices_db", "node19-garr-pa1"], ["invoices", "node19-garr-pa1"], ["products_db", "node19-garr-pa1"], ["products", "node19-garr-pa1"], ["customers_db", "node19-garr-pa1"], ["customers", "node19-garr-pa1"]], "ToRemove": [], "ToMigrate": []}, "ToAdd": 8, "avg-to_add": 60.81063610315323, "actuate": 486.4851710796356, "total_time": 1527.8418998718262}, {"cmd": "add /home/ubuntu/FogArmX/GARR/apps/docker-swarm-demo-48/", "app": "/home/ubuntu/FogArmX/GARR/apps/docker-swarm-demo-48", "timestamp": 1655669279.6794376, "fogbrain": 0.1910104751586914, "Placement": {"application": "docker-swarm-demo-48", "ToAdd": [["api-gateway", "node19-garr-pa1"], ["webapp", "node19-garr-pa1"], ["invoices_db", "node19-garr-pa1"], ["invoices", "node19-garr-pa1"], ["products_db", "node19-garr-pa1"], ["products", "node19-garr-pa1"], ["customers_db", "node19-garr-pa1"], ["customers", "node19-garr-pa1"]], "ToRemove": [], "ToMigrate": []}, "ToAdd": 8, "avg-to_add": 64.42869839072227, "actuate": 515.4296586513519, "total_time": 1559.2486617565155}, {"cmd": "add /home/ubuntu/FogArmX/GARR/apps/docker-swarm-demo-49/", "app": "/home/ubuntu/FogArmX/GARR/apps/docker-swarm-demo-49", "timestamp": 1655670846.464374, "fogbrain": 0.20249629020690918, "Placement": {"application": "docker-swarm-demo-49", "ToAdd": [["api-gateway", "node19-garr-pa1"], ["webapp", "node19-garr-pa1"], ["invoices_db", "node19-garr-pa1"], ["invoices", "node19-garr-pa1"], ["products_db", "node19-garr-pa1"], ["products", "node19-garr-pa1"], ["customers_db", "node19-garr-pa1"], ["customers", "node19-garr-pa1"]], "ToRemove": [], "ToMigrate": []}, "ToAdd": 8, "avg-to_add": 62.5316207408905, "actuate": 500.2530150413513, "total_time": 1614.2547097206116}, {"cmd": "exec docker-swarm-demo-0", "app": "/home/ubuntu/FogArmX/GARR/apps/docker-swarm-demo-0", "timestamp": 1655672501.0398352, "fogbrain": 0.23816132545471191, "Placement": {"application": "docker-swarm-demo-0", "ToAdd": [], "ToRemove": [], "ToMigrate": [["api-gateway", "node0-garr-pa1", "node19-garr-pa1"], ["webapp", "node0-garr-pa1", "node19-garr-pa1"], ["invoices_db", "node0-garr-pa1", "node19-garr-pa1"], ["products_db", "node0-garr-pa1", "node19-garr-pa1"], ["products", "node0-garr-pa1", "node19-garr-pa1"], ["customers_db", "node0-garr-pa1", "node19-garr-pa1"]]}, "ToMigrate": 6, "avg-to_migrate": 3.1198039849599204, "actuate": 113.12543892860413, "total_time": 1112.5863602161407}, {"cmd": "exec docker-swarm-demo-1", "app": "/home/ubuntu/FogArmX/GARR/apps/docker-swarm-demo-1", "timestamp": 1655673616.011557, "fogbrain": 0.2030177116394043, "Placement": {"application": "docker-swarm-demo-1", "ToAdd": [], "ToRemove": [["products", "node3-garr-to1"]], "ToMigrate": [["webapp", "node3-garr-to1", "node19-garr-pa1"], ["invoices_db", "node3-garr-to1", "node19-garr-pa1"], ["invoices", "node3-garr-to1", "node19-garr-pa1"], ["products_db", "node3-garr-to1", "node19-garr-pa1"], ["customers_db", "node3-garr-to1", "node19-garr-pa1"], ["customers", "node3-garr-to1", "node19-garr-pa1"]]}, "ToMigrate": 6, "avg-to_migrate": 3.5942355394363403, "ToRemove": 1, "avg-to_remove": 0.2928462028503418, "actuate": 111.56431818008423, "total_time": 1128.4992616176605}, {"cmd": "exec docker-swarm-demo-2", "app": "/home/ubuntu/FogArmX/GARR/apps/docker-swarm-demo-2", "timestamp": 1655674746.8926084, "fogbrain": 0.13698124885559082, "Placement": {"application": "docker-swarm-demo-2", "ToAdd": [], "ToRemove": [["api-gateway", "node12-garr-to1"]], "ToMigrate": [["webapp", "node12-garr-to1", "node19-garr-pa1"], ["invoices_db", "node12-garr-to1", "node19-garr-pa1"], ["products_db", "node12-garr-to1", "node19-garr-pa1"], ["products", "node12-garr-to1", "node19-garr-pa1"], ["customers_db", "node12-garr-to1", "node19-garr-pa1"], ["customers", "node12-garr-to1", "node19-garr-pa1"]]}, "ToMigrate": 6, "avg-to_migrate": 3.271687865257263, "ToRemove": 1, "avg-to_remove": 0.2901480197906494, "actuate": 129.71971344947815, "total_time": 988.9103071689606}, {"cmd": "exec docker-swarm-demo-3", "app": "/home/ubuntu/FogArmX/GARR/apps/docker-swarm-demo-3", "timestamp": 1655675738.1303296, "fogbrain": 0.19078469276428223, "Placement": {"application": "docker-swarm-demo-3", "ToAdd": [["webapp", "node10-garr-ct1"]], "ToRemove": [], "ToMigrate": [["api-gateway", "node12-garr-to1", "node10-garr-ct1"], ["invoices_db", "node12-garr-to1", "node10-garr-ct1"], ["invoices", "node12-garr-to1", "node10-garr-ct1"], ["products_db", "node12-garr-to1", "node10-garr-ct1"], ["products", "node12-garr-to1", "node10-garr-ct1"], ["customers_db", "node12-garr-to1", "node10-garr-ct1"], ["customers", "node12-garr-to1", "node10-garr-ct1"]]}, "ToAdd": 1, "avg-to_add": 445.5975875854492, "ToMigrate": 7, "avg-to_migrate": 3.969090563910348, "actuate": 601.7523386478424, "total_time": 1640.207215309143}, {"cmd": "exec docker-swarm-demo-4", "app": "/home/ubuntu/FogArmX/GARR/apps/docker-swarm-demo-4", "timestamp": 1655677380.5720775, "fogbrain": 0.21342253684997559, "Placement": {"application": "docker-swarm-demo-4", "ToAdd": [["api-gateway", "node10-garr-ct1"]], "ToRemove": [], "ToMigrate": [["webapp", "node14-garr-ct1", "node10-garr-ct1"], ["invoices_db", "node14-garr-ct1", "node10-garr-ct1"], ["invoices", "node14-garr-ct1", "node10-garr-ct1"], ["products_db", "node14-garr-ct1", "node10-garr-ct1"], ["products", "node14-garr-ct1", "node10-garr-ct1"], ["customers_db", "node14-garr-ct1", "node10-garr-ct1"], ["customers", "node14-garr-ct1", "node10-garr-ct1"]]}, "ToAdd": 1, "avg-to_add": 383.649671792984, "ToMigrate": 7, "avg-to_migrate": 2.7415225165230885, "actuate": 510.3618347644806, "total_time": 1486.0054047107697}, {"cmd": "exec docker-swarm-demo-5", "app": "/home/ubuntu/FogArmX/GARR/apps/docker-swarm-demo-5", "timestamp": 1655678868.6265118, "fogbrain": 0.19713425636291504, "Placement": {"application": "docker-swarm-demo-5", "ToAdd": [["webapp", "node10-garr-ct1"]], "ToRemove": [], "ToMigrate": [["api-gateway", "node2-garr-to1", "node10-garr-ct1"], ["invoices_db", "node2-garr-to1", "node10-garr-ct1"], ["invoices", "node2-garr-to1", "node10-garr-ct1"], ["products_db", "node2-garr-to1", "node10-garr-ct1"], ["products", "node2-garr-to1", "node10-garr-ct1"], ["customers_db", "node2-garr-to1", "node10-garr-ct1"], ["customers", "node2-garr-to1", "node10-garr-ct1"]]}, "ToAdd": 1, "avg-to_add": 406.3845205307007, "ToMigrate": 7, "avg-to_migrate": 2.5641094616481235, "actuate": 526.9942564964294, "total_time": 1528.8661835193634}, {"cmd": "exec docker-swarm-demo-6", "app": "/home/ubuntu/FogArmX/GARR/apps/docker-swarm-demo-6", "timestamp": 1655680399.465696, "fogbrain": 0.1994614601135254, "Placement": {"application": "docker-swarm-demo-6", "ToAdd": [], "ToRemove": [], "ToMigrate": [["api-gateway", "node12-garr-pa1", "node10-garr-ct1"], ["webapp", "node12-garr-pa1", "node10-garr-ct1"], ["invoices_db", "node12-garr-pa1", "node10-garr-ct1"], ["invoices", "node12-garr-pa1", "node10-garr-ct1"], ["products_db", "node12-garr-pa1", "node10-garr-ct1"], ["products", "node12-garr-pa1", "node10-garr-ct1"], ["customers_db", "node12-garr-pa1", "node10-garr-ct1"], ["customers", "node12-garr-pa1", "node10-garr-ct1"]]}, "ToMigrate": 8, "avg-to_migrate": 2.219016283750534, "actuate": 148.6509566307068, "total_time": 1204.6799573898315}, {"cmd": "exec docker-swarm-demo-7", "app": "/home/ubuntu/FogArmX/GARR/apps/docker-swarm-demo-7", "timestamp": 1655681606.6584184, "fogbrain": 0.23877763748168945, "Placement": {"application": "docker-swarm-demo-7", "ToAdd": [], "ToRemove": [["invoices", "node8-garr-to1"], ["customers", "node8-garr-to1"]], "ToMigrate": [["api-gateway", "node8-garr-to1", "node10-garr-ct1"], ["webapp", "node8-garr-to1", "node10-garr-ct1"], ["invoices_db", "node8-garr-to1", "node10-garr-ct1"], ["products_db", "node8-garr-to1", "node10-garr-ct1"], ["products", "node8-garr-to1", "node10-garr-ct1"], ["customers_db", "node8-garr-to1", "node10-garr-ct1"]]}, "ToMigrate": 6, "avg-to_migrate": 2.840104659398397, "ToRemove": 2, "avg-to_remove": 0.17010533809661865, "actuate": 102.84216904640198, "total_time": 573.0271410942078}, {"cmd": "exec docker-swarm-demo-8", "app": "/home/ubuntu/FogArmX/GARR/apps/docker-swarm-demo-8", "timestamp": 1655682180.6196349, "fogbrain": 0.07870936393737793, "Placement": {"application": "docker-swarm-demo-8", "ToAdd": [], "ToRemove": [["invoices", "node8-garr-to1"]], "ToMigrate": [["api-gateway", "node8-garr-to1", "node10-garr-ct1"], ["invoices_db", "node8-garr-to1", "node10-garr-ct1"], ["products_db", "node8-garr-to1", "node10-garr-ct1"], ["products", "node8-garr-to1", "node10-garr-ct1"], ["customers_db", "node8-garr-to1", "node10-garr-ct1"]]}, "ToMigrate": 5, "avg-to_migrate": 3.2736204147338865, "ToRemove": 1, "avg-to_remove": 0.12999439239501953, "actuate": 82.76243448257446, "total_time": 645.9920258522034}, {"cmd": "exec docker-swarm-demo-9", "app": "/home/ubuntu/FogArmX/GARR/apps/docker-swarm-demo-9", "timestamp": 1655682827.447203, "fogbrain": 0.08527398109436035, "Placement": {"application": "docker-swarm-demo-9", "ToAdd": [], "ToRemove": [["webapp", "node13-garr-ct1"]], "ToMigrate": [["api-gateway", "node13-garr-ct1", "node10-garr-ct1"], ["invoices_db", "node13-garr-ct1", "node10-garr-ct1"], ["invoices", "node13-garr-ct1", "node10-garr-ct1"], ["products_db", "node13-garr-ct1", "node10-garr-ct1"], ["products", "node13-garr-ct1", "node10-garr-ct1"], ["customers_db", "node13-garr-ct1", "node10-garr-ct1"], ["customers", "node13-garr-ct1", "node10-garr-ct1"]]}, "ToMigrate": 7, "avg-to_migrate": 2.490301643099104, "ToRemove": 1, "avg-to_remove": 0.1253681182861328, "actuate": 124.51357054710388, "total_time": 673.0257382392883}, {"cmd": "exec docker-swarm-demo-10", "app": "/home/ubuntu/FogArmX/GARR/apps/docker-swarm-demo-10", "timestamp": 1655683501.4426906, "fogbrain": 0.08221650123596191, "Placement": {"application": "docker-swarm-demo-10", "ToAdd": [["products", "node10-garr-ct1"]], "ToRemove": [], "ToMigrate": [["api-gateway", "node13-garr-ct1", "node10-garr-ct1"], ["webapp", "node13-garr-ct1", "node10-garr-ct1"], ["invoices_db", "node13-garr-ct1", "node10-garr-ct1"], ["invoices", "node13-garr-ct1", "node10-garr-ct1"], ["products_db", "node13-garr-ct1", "node10-garr-ct1"], ["customers_db", "node13-garr-ct1", "node10-garr-ct1"], ["customers", "node13-garr-ct1", "node10-garr-ct1"]]}, "ToAdd": 1, "avg-to_add": 179.38591480255127, "ToMigrate": 7, "avg-to_migrate": 2.439481292452131, "actuate": 301.17701268196106, "total_time": 843.3068246841431}, {"cmd": "exec docker-swarm-demo-11", "app": "/home/ubuntu/FogArmX/GARR/apps/docker-swarm-demo-11", "timestamp": 1655684345.709069, "fogbrain": 0.07858610153198242, "Placement": {"application": "docker-swarm-demo-11", "ToAdd": [["api-gateway", "node10-garr-ct1"], ["invoices", "node10-garr-ct1"]], "ToRemove": [["products", "node18-garr-pa1"]], "ToMigrate": [["webapp", "node18-garr-pa1", "node10-garr-ct1"], ["invoices_db", "node18-garr-pa1", "node10-garr-ct1"], ["products_db", "node18-garr-pa1", "node10-garr-ct1"], ["customers_db", "node18-garr-pa1", "node10-garr-ct1"], ["customers", "node18-garr-pa1", "node10-garr-ct1"]]}, "ToAdd": 2, "avg-to_add": 115.69090723991394, "ToMigrate": 5, "avg-to_migrate": 3.889270544052124, "ToRemove": 1, "avg-to_remove": 0.181884765625, "actuate": 336.7109043598175, "total_time": 886.9904911518097}, {"cmd": "exec docker-swarm-demo-12", "app": "/home/ubuntu/FogArmX/GARR/apps/docker-swarm-demo-12", "timestamp": 1655685233.4689884, "fogbrain": 0.07463479042053223, "Placement": {"application": "docker-swarm-demo-12", "ToAdd": [], "ToRemove": [["api-gateway", "node18-garr-pa1"], ["products", "node18-garr-pa1"]], "ToMigrate": [["webapp", "node18-garr-pa1", "node10-garr-ct1"], ["invoices_db", "node18-garr-pa1", "node10-garr-ct1"], ["invoices", "node18-garr-pa1", "node10-garr-ct1"], ["products_db", "node18-garr-pa1", "node10-garr-ct1"], ["customers_db", "node18-garr-pa1", "node10-garr-ct1"], ["customers", "node18-garr-pa1", "node10-garr-ct1"]]}, "ToMigrate": 6, "avg-to_migrate": 3.3517739375432334, "ToRemove": 2, "avg-to_remove": 0.06307721138000488, "actuate": 113.43470573425293, "total_time": 663.3444571495056}, {"cmd": "exec docker-swarm-demo-13", "app": "/home/ubuntu/FogArmX/GARR/apps/docker-swarm-demo-13", "timestamp": 1655685898.0429306, "fogbrain": 0.08374810218811035, "Placement": {"application": "docker-swarm-demo-13", "ToAdd": [], "ToRemove": [["webapp", "node18-garr-pa1"]], "ToMigrate": [["api-gateway", "node18-garr-pa1", "node10-garr-ct1"], ["invoices_db", "node18-garr-pa1", "node10-garr-ct1"], ["invoices", "node18-garr-pa1", "node10-garr-ct1"], ["products_db", "node18-garr-pa1", "node10-garr-ct1"], ["products", "node18-garr-pa1", "node10-garr-ct1"], ["customers_db", "node18-garr-pa1", "node10-garr-ct1"], ["customers", "node18-garr-pa1", "node10-garr-ct1"]]}, "ToMigrate": 7, "avg-to_migrate": 2.6991538320268904, "ToRemove": 1, "avg-to_remove": 0.26834774017333984, "actuate": 146.9822473526001, "total_time": 729.0107092857361}, {"cmd": "exec docker-swarm-demo-14", "app": "/home/ubuntu/FogArmX/GARR/apps/docker-swarm-demo-14", "timestamp": 1655686628.0211353, "fogbrain": 0.08333110809326172, "Placement": {"application": "docker-swarm-demo-14", "ToAdd": [["api-gateway", "node10-garr-ct1"], ["invoices", "node10-garr-ct1"]], "ToRemove": [["customers", "node11-garr-ct1"]], "ToMigrate": [["webapp", "node11-garr-ct1", "node10-garr-ct1"], ["invoices_db", "node11-garr-ct1", "node10-garr-ct1"], ["products_db", "node11-garr-ct1", "node10-garr-ct1"], ["products", "node11-garr-ct1", "node10-garr-ct1"], ["customers_db", "node11-garr-ct1", "node10-garr-ct1"]]}, "ToAdd": 2, "avg-to_add": 122.68552207946777, "ToMigrate": 5, "avg-to_migrate": 3.4794418811798096, "ToRemove": 1, "avg-to_remove": 0.22485566139221191, "actuate": 331.4457595348358, "total_time": 882.9362897872925}, {"cmd": "exec docker-swarm-demo-15", "app": "/home/ubuntu/FogArmX/GARR/apps/docker-swarm-demo-15", "timestamp": 1655687512.0221922, "fogbrain": 0.08553957939147949, "Placement": {"application": "docker-swarm-demo-15", "ToAdd": [], "ToRemove": [["webapp", "node11-garr-ct1"]], "ToMigrate": [["api-gateway", "node11-garr-ct1", "node10-garr-ct1"], ["invoices_db", "node11-garr-ct1", "node10-garr-ct1"], ["products_db", "node11-garr-ct1", "node10-garr-ct1"], ["products", "node11-garr-ct1", "node10-garr-ct1"], ["customers_db", "node11-garr-ct1", "node10-garr-ct1"], ["customers", "node11-garr-ct1", "node10-garr-ct1"]]}, "ToMigrate": 6, "avg-to_migrate": 3.1054251194000244, "ToRemove": 1, "avg-to_remove": 1.2805771827697754, "actuate": 114.80311584472656, "total_time": 603.7513675689697}, {"cmd": "exec docker-swarm-demo-16", "app": "/home/ubuntu/FogArmX/GARR/apps/docker-swarm-demo-16", "timestamp": 1655688116.6799345, "fogbrain": 0.08749270439147949, "Placement": {"application": "docker-swarm-demo-16", "ToAdd": [], "ToRemove": [], "ToMigrate": [["api-gateway", "node10-garr-to1", "node10-garr-ct1"], ["webapp", "node10-garr-to1", "node10-garr-ct1"], ["invoices_db", "node10-garr-to1", "node10-garr-ct1"], ["invoices", "node10-garr-to1", "node10-garr-ct1"], ["products_db", "node10-garr-to1", "node10-garr-ct1"], ["products", "node10-garr-to1", "node10-garr-ct1"], ["customers_db", "node10-garr-to1", "node10-garr-ct1"], ["customers", "node10-garr-to1", "node10-garr-ct1"]]}, "ToMigrate": 8, "avg-to_migrate": 2.403527945280075, "actuate": 144.38017201423645, "total_time": 654.7495996952057}, {"cmd": "exec docker-swarm-demo-17", "app": "/home/ubuntu/FogArmX/GARR/apps/docker-swarm-demo-17", "timestamp": 1655688772.434635, "fogbrain": 0.08377957344055176, "Placement": {"application": "docker-swarm-demo-17", "ToAdd": [], "ToRemove": [], "ToMigrate": [["api-gateway", "node10-garr-to1", "node10-garr-ct1"], ["webapp", "node10-garr-to1", "node10-garr-ct1"], ["invoices_db", "node10-garr-to1", "node10-garr-ct1"], ["products_db", "node10-garr-to1", "node10-garr-ct1"], ["products", "node10-garr-to1", "node10-garr-ct1"], ["customers_db", "node10-garr-to1", "node10-garr-ct1"], ["customers", "node10-garr-to1", "node10-garr-ct1"]]}, "ToMigrate": 7, "avg-to_migrate": 2.555694614137922, "actuate": 124.90565729141235, "total_time": 681.0383334159851}, {"cmd": "exec docker-swarm-demo-18", "app": "/home/ubuntu/FogArmX/GARR/apps/docker-swarm-demo-18", "timestamp": 1655689454.6237872, "fogbrain": 0.0734102725982666, "Placement": {"application": "docker-swarm-demo-18", "ToAdd": [], "ToRemove": [], "ToMigrate": [["webapp", "node10-garr-to1", "node10-garr-ct1"], ["invoices_db", "node10-garr-to1", "node10-garr-ct1"], ["invoices", "node10-garr-to1", "node10-garr-ct1"], ["products_db", "node10-garr-to1", "node10-garr-ct1"], ["products", "node10-garr-to1", "node10-garr-ct1"], ["customers_db", "node10-garr-to1", "node10-garr-ct1"], ["customers", "node10-garr-to1", "node10-garr-ct1"]]}, "ToMigrate": 7, "avg-to_migrate": 2.8616065297807967, "actuate": 129.0322549343109, "total_time": 704.449492931366}, {"cmd": "exec docker-swarm-demo-19", "app": "/home/ubuntu/FogArmX/GARR/apps/docker-swarm-demo-19", "timestamp": 1655690160.2065246, "fogbrain": 0.08753418922424316, "Placement": {"application": "docker-swarm-demo-19", "ToAdd": [], "ToRemove": [["api-gateway", "node10-garr-to1"]], "ToMigrate": [["webapp", "node10-garr-to1", "node10-garr-ct1"], ["invoices_db", "node10-garr-to1", "node10-garr-ct1"], ["invoices", "node10-garr-to1", "node10-garr-ct1"], ["products_db", "node10-garr-to1", "node10-garr-ct1"], ["products", "node10-garr-to1", "node10-garr-ct1"], ["customers_db", "node10-garr-to1", "node10-garr-ct1"], ["customers", "node10-garr-to1", "node10-garr-ct1"]]}, "ToMigrate": 7, "avg-to_migrate": 2.505758694240025, "ToRemove": 1, "avg-to_remove": 0.1852419376373291, "actuate": 122.9461088180542, "total_time": 729.9232110977173}, {"cmd": "exec docker-swarm-demo-20", "app": "/home/ubuntu/FogArmX/GARR/apps/docker-swarm-demo-20", "timestamp": 1655691083.0906713, "fogbrain": 0.08232688903808594, "Placement": {"application": "docker-swarm-demo-20", "ToAdd": [["invoices", "node10-garr-ct1"]], "ToRemove": [], "ToMigrate": [["api-gateway", "node19-garr-ct1", "node10-garr-ct1"], ["webapp", "node19-garr-ct1", "node10-garr-ct1"], ["invoices_db", "node19-garr-ct1", "node10-garr-ct1"], ["products_db", "node19-garr-ct1", "node10-garr-ct1"], ["products", "node19-garr-ct1", "node10-garr-ct1"], ["customers_db", "node19-garr-ct1", "node10-garr-ct1"], ["customers", "node19-garr-ct1", "node10-garr-ct1"]]}, "ToAdd": 1, "avg-to_add": 218.48415780067444, "ToMigrate": 7, "avg-to_migrate": 2.6159066472734724, "actuate": 346.6288194656372, "total_time": 919.2809133529663}, {"cmd": "exec docker-swarm-demo-21", "app": "/home/ubuntu/FogArmX/GARR/apps/docker-swarm-demo-21", "timestamp": 1655692195.8269436, "fogbrain": 0.09156656265258789, "Placement": {"application": "docker-swarm-demo-21", "ToAdd": [], "ToRemove": [["webapp", "node19-garr-ct1"]], "ToMigrate": [["api-gateway", "node19-garr-ct1", "node10-garr-ct1"], ["invoices_db", "node19-garr-ct1", "node10-garr-ct1"], ["invoices", "node19-garr-ct1", "node10-garr-ct1"], ["products_db", "node19-garr-ct1", "node10-garr-ct1"], ["products", "node19-garr-ct1", "node10-garr-ct1"], ["customers_db", "node19-garr-ct1", "node10-garr-ct1"], ["customers", "node19-garr-ct1", "node10-garr-ct1"]]}, "ToMigrate": 7, "avg-to_migrate": 2.980975730078561, "ToRemove": 1, "avg-to_remove": 0.17872214317321777, "actuate": 132.24878525733948, "total_time": 695.5627210140228}, {"cmd": "exec docker-swarm-demo-22", "app": "/home/ubuntu/FogArmX/GARR/apps/docker-swarm-demo-22", "timestamp": 1655693071.4496725, "fogbrain": 0.0894465446472168, "Placement": {"application": "docker-swarm-demo-22", "ToAdd": [["customers", "node10-garr-ct1"]], "ToRemove": [["invoices", "node19-garr-ct1"]], "ToMigrate": [["api-gateway", "node19-garr-ct1", "node10-garr-ct1"], ["webapp", "node19-garr-ct1", "node10-garr-ct1"], ["invoices_db", "node19-garr-ct1", "node10-garr-ct1"], ["products_db", "node19-garr-ct1", "node10-garr-ct1"], ["products", "node19-garr-ct1", "node10-garr-ct1"], ["customers_db", "node19-garr-ct1", "node10-garr-ct1"]]}, "ToAdd": 1, "avg-to_add": 222.1591670513153, "ToMigrate": 6, "avg-to_migrate": 3.451300263404846, "ToRemove": 1, "avg-to_remove": 0.17521190643310547, "actuate": 335.0600378513336, "total_time": 868.8231446743011}, {"cmd": "exec docker-swarm-demo-23", "app": "/home/ubuntu/FogArmX/GARR/apps/docker-swarm-demo-23", "timestamp": 1655694104.112111, "fogbrain": 0.17025494575500488, "Placement": {"application": "docker-swarm-demo-23", "ToAdd": [["api-gateway", "node10-garr-ct1"], ["customers", "node10-garr-ct1"]], "ToRemove": [], "ToMigrate": [["webapp", "node19-garr-ct1", "node10-garr-ct1"], ["invoices_db", "node19-garr-ct1", "node10-garr-ct1"], ["invoices", "node19-garr-ct1", "node10-garr-ct1"], ["products_db", "node19-garr-ct1", "node10-garr-ct1"], ["products", "node19-garr-ct1", "node10-garr-ct1"], ["customers_db", "node19-garr-ct1", "node10-garr-ct1"]]}, "ToAdd": 2, "avg-to_add": 106.81049704551697, "ToMigrate": 6, "avg-to_migrate": 3.1329335371653237, "actuate": 322.6132426261902, "total_time": 833.553549528122}, {"cmd": "exec docker-swarm-demo-24", "app": "/home/ubuntu/FogArmX/GARR/apps/docker-swarm-demo-24", "timestamp": 1655695104.1732404, "fogbrain": 0.07320928573608398, "Placement": {"application": "docker-swarm-demo-24", "ToAdd": [["webapp", "node10-garr-ct1"]], "ToRemove": [], "ToMigrate": [["api-gateway", "node4-garr-ct1", "node10-garr-ct1"], ["invoices_db", "node4-garr-ct1", "node10-garr-ct1"], ["invoices", "node4-garr-ct1", "node10-garr-ct1"], ["products_db", "node4-garr-ct1", "node10-garr-ct1"], ["products", "node4-garr-ct1", "node10-garr-ct1"], ["customers_db", "node4-garr-ct1", "node10-garr-ct1"], ["customers", "node4-garr-ct1", "node10-garr-ct1"]]}, "ToAdd": 1, "avg-to_add": 205.54965019226074, "ToMigrate": 7, "avg-to_migrate": 2.44580010005406, "actuate": 326.4826190471649, "total_time": 841.2805202007294}, {"cmd": "exec docker-swarm-demo-25", "app": "/home/ubuntu/FogArmX/GARR/apps/docker-swarm-demo-25", "timestamp": 1655696096.1359596, "fogbrain": 0.09524774551391602, "Placement": {"application": "docker-swarm-demo-25", "ToAdd": [["webapp", "node10-garr-ct1"], ["invoices", "node10-garr-ct1"]], "ToRemove": [], "ToMigrate": [["api-gateway", "node4-garr-ct1", "node10-garr-ct1"], ["invoices_db", "node4-garr-ct1", "node10-garr-ct1"], ["products_db", "node4-garr-ct1", "node10-garr-ct1"], ["products", "node4-garr-ct1", "node10-garr-ct1"], ["customers_db", "node4-garr-ct1", "node10-garr-ct1"], ["customers", "node4-garr-ct1", "node10-garr-ct1"]]}, "ToAdd": 2, "avg-to_add": 100.33638417720795, "ToMigrate": 6, "avg-to_migrate": 2.8298229773839316, "actuate": 302.5888726711273, "total_time": 763.0455470085144}, {"cmd": "exec docker-swarm-demo-26", "app": "/home/ubuntu/FogArmX/GARR/apps/docker-swarm-demo-26", "timestamp": 1655696993.9831874, "fogbrain": 0.16237282752990723, "Placement": {"application": "docker-swarm-demo-26", "ToAdd": [], "ToRemove": [], "ToMigrate": [["webapp", "node4-garr-ct1", "node10-garr-ct1"], ["invoices_db", "node4-garr-ct1", "node10-garr-ct1"], ["invoices", "node4-garr-ct1", "node10-garr-ct1"], ["products_db", "node4-garr-ct1", "node10-garr-ct1"], ["products", "node4-garr-ct1", "node10-garr-ct1"], ["customers_db", "node4-garr-ct1", "node10-garr-ct1"], ["customers", "node4-garr-ct1", "node10-garr-ct1"]]}, "ToMigrate": 7, "avg-to_migrate": 2.4474409988948276, "actuate": 121.00564360618591, "total_time": 653.3755497932434}, {"cmd": "exec docker-swarm-demo-27", "app": "/home/ubuntu/FogArmX/GARR/apps/docker-swarm-demo-27", "timestamp": 1655697795.4281087, "fogbrain": 0.06794238090515137, "Placement": {"application": "docker-swarm-demo-27", "ToAdd": [], "ToRemove": [], "ToMigrate": [["api-gateway", "node4-garr-ct1", "node10-garr-ct1"], ["webapp", "node4-garr-ct1", "node10-garr-ct1"], ["invoices_db", "node4-garr-ct1", "node10-garr-ct1"], ["invoices", "node4-garr-ct1", "node10-garr-ct1"], ["products_db", "node4-garr-ct1", "node10-garr-ct1"], ["products", "node4-garr-ct1", "node10-garr-ct1"], ["customers_db", "node4-garr-ct1", "node10-garr-ct1"], ["customers", "node4-garr-ct1", "node10-garr-ct1"]]}, "ToMigrate": 8, "avg-to_migrate": 2.099275767803192, "actuate": 140.20802235603333, "total_time": 640.4349677562714}, {"cmd": "exec docker-swarm-demo-28", "app": "/home/ubuntu/FogArmX/GARR/apps/docker-swarm-demo-28", "timestamp": 1655698592.5754485, "fogbrain": 0.1468040943145752, "Placement": {"application": "docker-swarm-demo-28", "ToAdd": [["customers", "node10-garr-ct1"]], "ToRemove": [], "ToMigrate": [["api-gateway", "node4-garr-ct1", "node10-garr-ct1"], ["webapp", "node4-garr-ct1", "node10-garr-ct1"], ["invoices_db", "node4-garr-ct1", "node10-garr-ct1"], ["invoices", "node4-garr-ct1", "node10-garr-ct1"], ["products_db", "node4-garr-ct1", "node10-garr-ct1"], ["products", "node4-garr-ct1", "node10-garr-ct1"], ["customers_db", "node4-garr-ct1", "node10-garr-ct1"]]}, "ToAdd": 1, "avg-to_add": 187.0883870124817, "ToMigrate": 7, "avg-to_migrate": 2.583857842854091, "actuate": 316.9233739376068, "total_time": 792.9408223628998}, {"cmd": "exec docker-swarm-demo-29", "app": "/home/ubuntu/FogArmX/GARR/apps/docker-swarm-demo-29", "timestamp": 1655699533.9086082, "fogbrain": 0.1895129680633545, "Placement": {"application": "docker-swarm-demo-29", "ToAdd": [], "ToRemove": [], "ToMigrate": [["api-gateway", "node13-garr-pa1", "node10-garr-ct1"], ["webapp", "node13-garr-pa1", "node10-garr-ct1"], ["invoices_db", "node13-garr-pa1", "node10-garr-ct1"], ["invoices", "node13-garr-pa1", "node10-garr-ct1"], ["products_db", "node13-garr-pa1", "node10-garr-ct1"], ["products", "node13-garr-pa1", "node10-garr-ct1"], ["customers_db", "node13-garr-pa1", "node10-garr-ct1"], ["customers", "node13-garr-pa1", "node10-garr-ct1"]]}, "ToMigrate": 8, "avg-to_migrate": 2.3878098130226135, "actuate": 156.7725749015808, "total_time": 634.3289248943329}, {"cmd": "exec docker-swarm-demo-30", "app": "/home/ubuntu/FogArmX/GARR/apps/docker-swarm-demo-30", "timestamp": 1655700336.3940861, "fogbrain": 0.08867716789245605, "Placement": {"application": "docker-swarm-demo-30", "ToAdd": [["webapp", "node10-garr-ct1"]], "ToRemove": [["invoices", "node13-garr-pa1"]], "ToMigrate": [["invoices_db", "node13-garr-pa1", "node10-garr-ct1"], ["products_db", "node13-garr-pa1", "node10-garr-ct1"], ["products", "node13-garr-pa1", "node10-garr-ct1"], ["customers_db", "node13-garr-pa1", "node10-garr-ct1"], ["customers", "node13-garr-pa1", "node10-garr-ct1"]]}, "ToAdd": 1, "avg-to_add": 186.07961678504944, "ToMigrate": 5, "avg-to_migrate": 3.509171390533447, "ToRemove": 1, "avg-to_remove": 0.22942256927490234, "actuate": 281.1700942516327, "total_time": 725.49951171875}, {"cmd": "exec docker-swarm-demo-31", "app": "/home/ubuntu/FogArmX/GARR/apps/docker-swarm-demo-31", "timestamp": 1655701202.51788, "fogbrain": 0.14144539833068848, "Placement": {"application": "docker-swarm-demo-31", "ToAdd": [["webapp", "node10-garr-ct1"]], "ToRemove": [["customers", "node13-garr-pa1"]], "ToMigrate": [["api-gateway", "node13-garr-pa1", "node10-garr-ct1"], ["invoices_db", "node13-garr-pa1", "node10-garr-ct1"], ["invoices", "node13-garr-pa1", "node10-garr-ct1"], ["products_db", "node13-garr-pa1", "node10-garr-ct1"], ["products", "node13-garr-pa1", "node10-garr-ct1"], ["customers_db", "node13-garr-pa1", "node10-garr-ct1"]]}, "ToAdd": 1, "avg-to_add": 189.04947638511658, "ToMigrate": 6, "avg-to_migrate": 3.3658032417297363, "ToRemove": 1, "avg-to_remove": 0.18665194511413574, "actuate": 306.5228056907654, "total_time": 786.918781042099}, {"cmd": "exec docker-swarm-demo-32", "app": "/home/ubuntu/FogArmX/GARR/apps/docker-swarm-demo-32", "timestamp": 1655702136.2203634, "fogbrain": 0.1022641658782959, "Placement": {"application": "docker-swarm-demo-32", "ToAdd": [["webapp", "node10-garr-ct1"]], "ToRemove": [["invoices", "node13-garr-pa1"], ["customers", "node13-garr-pa1"]], "ToMigrate": [["api-gateway", "node13-garr-pa1", "node10-garr-ct1"], ["invoices_db", "node13-garr-pa1", "node10-garr-ct1"], ["products_db", "node13-garr-pa1", "node10-garr-ct1"], ["products", "node13-garr-pa1", "node10-garr-ct1"], ["customers_db", "node13-garr-pa1", "node10-garr-ct1"]]}, "ToAdd": 1, "avg-to_add": 177.304270029068, "ToMigrate": 5, "avg-to_migrate": 3.6097251415252685, "ToRemove": 2, "avg-to_remove": 0.09191334247589111, "actuate": 266.8285114765167, "total_time": 703.2403378486633}, {"cmd": "exec docker-swarm-demo-33", "app": "/home/ubuntu/FogArmX/GARR/apps/docker-swarm-demo-33", "timestamp": 1655702964.714608, "fogbrain": 0.0749962329864502, "Placement": {"application": "docker-swarm-demo-33", "ToAdd": [], "ToRemove": [["products", "node13-garr-pa1"]], "ToMigrate": [["api-gateway", "node13-garr-pa1", "node10-garr-ct1"], ["webapp", "node13-garr-pa1", "node10-garr-ct1"], ["invoices_db", "node13-garr-pa1", "node10-garr-ct1"], ["invoices", "node13-garr-pa1", "node10-garr-ct1"], ["products_db", "node13-garr-pa1", "node10-garr-ct1"], ["customers_db", "node13-garr-pa1", "node10-garr-ct1"], ["customers", "node13-garr-pa1", "node10-garr-ct1"]]}, "ToMigrate": 7, "avg-to_migrate": 2.567568676812308, "ToRemove": 1, "avg-to_remove": 0.12609601020812988, "actuate": 138.73749375343323, "total_time": 533.3252186775208}, {"cmd": "exec docker-swarm-demo-34", "app": "/home/ubuntu/FogArmX/GARR/apps/docker-swarm-demo-34", "timestamp": 1655703628.426802, "fogbrain": 0.10070967674255371, "Placement": {"application": "docker-swarm-demo-34", "ToAdd": [], "ToRemove": [["webapp", "node13-garr-pa1"]], "ToMigrate": [["api-gateway", "node13-garr-pa1", "node10-garr-ct1"], ["invoices_db", "node13-garr-pa1", "node10-garr-ct1"], ["invoices", "node13-garr-pa1", "node10-garr-ct1"], ["products_db", "node13-garr-pa1", "node10-garr-ct1"], ["products", "node13-garr-pa1", "node10-garr-ct1"], ["customers_db", "node13-garr-pa1", "node10-garr-ct1"], ["customers", "node13-garr-pa1", "node10-garr-ct1"]]}, "ToMigrate": 7, "avg-to_migrate": 2.7117177077702115, "ToRemove": 1, "avg-to_remove": 0.12885093688964844, "actuate": 135.4182116985321, "total_time": 530.2521574497223}, {"cmd": "exec docker-swarm-demo-35", "app": "/home/ubuntu/FogArmX/GARR/apps/docker-swarm-demo-35", "timestamp": 1655704285.4476936, "fogbrain": 0.08600401878356934, "Placement": {"application": "docker-swarm-demo-35", "ToAdd": [], "ToRemove": [["api-gateway", "node19-garr-to1"]], "ToMigrate": [["webapp", "node19-garr-to1", "node10-garr-ct1"], ["invoices_db", "node19-garr-to1", "node10-garr-ct1"], ["invoices", "node19-garr-to1", "node10-garr-ct1"], ["products_db", "node19-garr-to1", "node10-garr-ct1"], ["products", "node19-garr-to1", "node10-garr-ct1"], ["customers_db", "node19-garr-to1", "node10-garr-ct1"], ["customers", "node19-garr-to1", "node10-garr-ct1"]]}, "ToMigrate": 7, "avg-to_migrate": 2.8292311940874373, "ToRemove": 1, "avg-to_remove": 0.12624549865722656, "actuate": 124.65811610221863, "total_time": 521.1819176673889}, {"cmd": "exec docker-swarm-demo-36", "app": "/home/ubuntu/FogArmX/GARR/apps/docker-swarm-demo-36", "timestamp": 1655704944.3703415, "fogbrain": 0.2006373405456543, "Placement": {"application": "docker-swarm-demo-36", "ToAdd": [], "ToRemove": [["api-gateway", "node19-garr-to1"]], "ToMigrate": [["invoices_db", "node19-garr-to1", "node10-garr-ct1"], ["invoices", "node19-garr-to1", "node10-garr-ct1"], ["products_db", "node19-garr-to1", "node10-garr-ct1"], ["products", "node19-garr-to1", "node10-garr-ct1"], ["customers_db", "node19-garr-to1", "node10-garr-ct1"], ["customers", "node19-garr-to1", "node10-garr-ct1"]]}, "ToMigrate": 6, "avg-to_migrate": 2.880164543787638, "ToRemove": 1, "avg-to_remove": 0.19484782218933105, "actuate": 106.35383129119873, "total_time": 515.8671915531158}, {"cmd": "exec docker-swarm-demo-37", "app": "/home/ubuntu/FogArmX/GARR/apps/docker-swarm-demo-37", "timestamp": 1655705582.362735, "fogbrain": 0.16039776802062988, "Placement": {"application": "docker-swarm-demo-37", "ToAdd": [], "ToRemove": [["webapp", "node19-garr-to1"], ["customers", "node19-garr-to1"]], "ToMigrate": [["api-gateway", "node19-garr-to1", "node10-garr-ct1"], ["invoices_db", "node19-garr-to1", "node10-garr-ct1"], ["invoices", "node19-garr-to1", "node10-garr-ct1"], ["products_db", "node19-garr-to1", "node10-garr-ct1"], ["products", "node19-garr-to1", "node10-garr-ct1"], ["customers_db", "node19-garr-to1", "node10-garr-ct1"]]}, "ToMigrate": 6, "avg-to_migrate": 2.8481430610020957, "ToRemove": 2, "avg-to_remove": 0.08918941020965576, "actuate": 105.52348160743713, "total_time": 499.29143738746643}, {"cmd": "exec docker-swarm-demo-38", "app": "/home/ubuntu/FogArmX/GARR/apps/docker-swarm-demo-38", "timestamp": 1655706210.1835763, "fogbrain": 0.0867764949798584, "Placement": {"application": "docker-swarm-demo-38", "ToAdd": [], "ToRemove": [], "ToMigrate": [["api-gateway", "node19-garr-to1", "node10-garr-ct1"], ["webapp", "node19-garr-to1", "node10-garr-ct1"], ["invoices_db", "node19-garr-to1", "node10-garr-ct1"], ["invoices", "node19-garr-to1", "node10-garr-ct1"], ["products_db", "node19-garr-to1", "node10-garr-ct1"], ["products", "node19-garr-to1", "node10-garr-ct1"], ["customers_db", "node19-garr-to1", "node10-garr-ct1"], ["customers", "node19-garr-to1", "node10-garr-ct1"]]}, "ToMigrate": 8, "avg-to_migrate": 2.2731593549251556, "actuate": 142.31113290786743, "total_time": 499.0635223388672}, {"cmd": "exec docker-swarm-demo-39", "app": "/home/ubuntu/FogArmX/GARR/apps/docker-swarm-demo-39", "timestamp": 1655706830.0637138, "fogbrain": 0.0771341323852539, "Placement": {"application": "docker-swarm-demo-39", "ToAdd": [["products", "node10-garr-ct1"]], "ToRemove": [], "ToMigrate": [["api-gateway", "node19-garr-to1", "node10-garr-ct1"], ["webapp", "node19-garr-to1", "node10-garr-ct1"], ["invoices_db", "node19-garr-to1", "node10-garr-ct1"], ["invoices", "node19-garr-to1", "node10-garr-ct1"], ["products_db", "node19-garr-to1", "node10-garr-ct1"], ["customers_db", "node19-garr-to1", "node10-garr-ct1"], ["customers", "node19-garr-to1", "node10-garr-ct1"]]}, "ToAdd": 1, "avg-to_add": 160.73241901397705, "ToMigrate": 7, "avg-to_migrate": 2.7084084238324846, "actuate": 299.9075548648834, "total_time": 655.1059083938599}, {"cmd": "exec docker-swarm-demo-40", "app": "/home/ubuntu/FogArmX/GARR/apps/docker-swarm-demo-40", "timestamp": 1655707627.9591734, "fogbrain": 0.2689402103424072, "Placement": {"application": "docker-swarm-demo-40", "ToAdd": [], "ToRemove": [["webapp", "node19-garr-to1"]], "ToMigrate": [["api-gateway", "node19-garr-to1", "node10-garr-ct1"], ["invoices_db", "node19-garr-to1", "node10-garr-ct1"], ["invoices", "node19-garr-to1", "node10-garr-ct1"], ["products_db", "node19-garr-to1", "node10-garr-ct1"], ["products", "node19-garr-to1", "node10-garr-ct1"], ["customers_db", "node19-garr-to1", "node10-garr-ct1"], ["customers", "node19-garr-to1", "node10-garr-ct1"]]}, "ToMigrate": 7, "avg-to_migrate": 2.57693042073931, "ToRemove": 1, "avg-to_remove": 0.25524425506591797, "actuate": 129.2567708492279, "total_time": 698.817239522934}, {"cmd": "exec docker-swarm-demo-41", "app": "/home/ubuntu/FogArmX/GARR/apps/docker-swarm-demo-41", "timestamp": 1655708507.807791, "fogbrain": 0.17703557014465332, "Placement": {"application": "docker-swarm-demo-41", "ToAdd": [], "ToRemove": [], "ToMigrate": [["api-gateway", "node19-garr-to1", "node10-garr-ct1"], ["webapp", "node19-garr-to1", "node10-garr-ct1"], ["invoices_db", "node19-garr-to1", "node10-garr-ct1"], ["invoices", "node19-garr-to1", "node10-garr-ct1"], ["products_db", "node19-garr-to1", "node10-garr-ct1"], ["products", "node19-garr-to1", "node10-garr-ct1"], ["customers_db", "node19-garr-to1", "node10-garr-ct1"], ["customers", "node19-garr-to1", "node10-garr-ct1"]]}, "ToMigrate": 8, "avg-to_migrate": 2.1514468789100647, "actuate": 140.5730698108673, "total_time": 666.6564826965332}, {"cmd": "exec docker-swarm-demo-42", "app": "/home/ubuntu/FogArmX/GARR/apps/docker-swarm-demo-42", "timestamp": 1655709343.9459555, "fogbrain": 0.18149995803833008, "Placement": {"application": "docker-swarm-demo-42", "ToAdd": [["invoices", "node10-garr-ct1"]], "ToRemove": [["customers", "node19-garr-to1"]], "ToMigrate": [["api-gateway", "node19-garr-to1", "node10-garr-ct1"], ["webapp", "node19-garr-to1", "node10-garr-ct1"], ["invoices_db", "node19-garr-to1", "node10-garr-ct1"], ["products_db", "node19-garr-to1", "node10-garr-ct1"], ["products", "node19-garr-to1", "node10-garr-ct1"], ["customers_db", "node19-garr-to1", "node10-garr-ct1"]]}, "ToAdd": 1, "avg-to_add": 196.50702285766602, "ToMigrate": 6, "avg-to_migrate": 3.0037824312845864, "ToRemove": 1, "avg-to_remove": 0.22526884078979492, "actuate": 304.99343729019165, "total_time": 789.7048830986023}, {"cmd": "exec docker-swarm-demo-43", "app": "/home/ubuntu/FogArmX/GARR/apps/docker-swarm-demo-43", "timestamp": 1655710294.8200383, "fogbrain": 0.10838079452514648, "Placement": {"application": "docker-swarm-demo-43", "ToAdd": [], "ToRemove": [["api-gateway", "node19-garr-pa1"]], "ToMigrate": [["webapp", "node19-garr-pa1", "node10-garr-ct1"], ["invoices_db", "node19-garr-pa1", "node10-garr-ct1"], ["invoices", "node19-garr-pa1", "node10-garr-ct1"], ["products_db", "node19-garr-pa1", "node10-garr-ct1"], ["products", "node19-garr-pa1", "node10-garr-ct1"], ["customers_db", "node19-garr-pa1", "node10-garr-ct1"], ["customers", "node19-garr-pa1", "node10-garr-ct1"]]}, "ToMigrate": 7, "avg-to_migrate": 2.4953437532697404, "ToRemove": 1, "avg-to_remove": 0.24215149879455566, "actuate": 122.7436580657959, "total_time": 599.8352289199829}, {"cmd": "exec docker-swarm-demo-44", "app": "/home/ubuntu/FogArmX/GARR/apps/docker-swarm-demo-44", "timestamp": 1655711058.8392777, "fogbrain": 0.16945767402648926, "Placement": {"application": "docker-swarm-demo-44", "ToAdd": [["api-gateway", "node10-garr-ct1"], ["webapp", "node10-garr-ct1"]], "ToRemove": [], "ToMigrate": [["invoices_db", "node19-garr-pa1", "node10-garr-ct1"], ["invoices", "node19-garr-pa1", "node10-garr-ct1"], ["products_db", "node19-garr-pa1", "node10-garr-ct1"], ["products", "node19-garr-pa1", "node10-garr-ct1"], ["customers_db", "node19-garr-pa1", "node10-garr-ct1"], ["customers", "node19-garr-pa1", "node10-garr-ct1"]]}, "ToAdd": 2, "avg-to_add": 92.28343832492828, "ToMigrate": 6, "avg-to_migrate": 3.327813704808553, "actuate": 300.07537961006165, "total_time": 591.9022259712219}, {"cmd": "exec docker-swarm-demo-45", "app": "/home/ubuntu/FogArmX/GARR/apps/docker-swarm-demo-45", "timestamp": 1655711737.102336, "fogbrain": 0.0880270004272461, "Placement": {"application": "docker-swarm-demo-45", "ToAdd": [["webapp", "node10-garr-ct1"], ["invoices", "node10-garr-ct1"]], "ToRemove": [], "ToMigrate": [["api-gateway", "node19-garr-pa1", "node10-garr-ct1"], ["invoices_db", "node19-garr-pa1", "node10-garr-ct1"], ["products_db", "node19-garr-pa1", "node10-garr-ct1"], ["products", "node19-garr-pa1", "node10-garr-ct1"], ["customers_db", "node19-garr-pa1", "node10-garr-ct1"], ["customers", "node19-garr-pa1", "node10-garr-ct1"]]}, "ToAdd": 2, "avg-to_add": 63.21919918060303, "ToMigrate": 6, "avg-to_migrate": 3.174909790356954, "actuate": 245.31210160255432, "total_time": 494.72656416893005}, {"cmd": "exec docker-swarm-demo-46", "app": "/home/ubuntu/FogArmX/GARR/apps/docker-swarm-demo-46", "timestamp": 1655712315.3458505, "fogbrain": 0.15676307678222656, "Placement": {"application": "docker-swarm-demo-46", "ToAdd": [["products", "node10-garr-ct1"]], "ToRemove": [], "ToMigrate": [["api-gateway", "node19-garr-pa1", "node10-garr-ct1"], ["webapp", "node19-garr-pa1", "node10-garr-ct1"], ["invoices_db", "node19-garr-pa1", "node10-garr-ct1"], ["invoices", "node19-garr-pa1", "node10-garr-ct1"], ["products_db", "node19-garr-pa1", "node10-garr-ct1"], ["customers_db", "node19-garr-pa1", "node10-garr-ct1"], ["customers", "node19-garr-pa1", "node10-garr-ct1"]]}, "ToAdd": 1, "avg-to_add": 121.24547553062439, "ToMigrate": 7, "avg-to_migrate": 2.600078821182251, "actuate": 249.48712515830994, "total_time": 500.79381275177}, {"cmd": "exec docker-swarm-demo-47", "app": "/home/ubuntu/FogArmX/GARR/apps/docker-swarm-demo-47", "timestamp": 1655712892.5844681, "fogbrain": 0.06768393516540527, "Placement": {"application": "docker-swarm-demo-47", "ToAdd": [], "ToRemove": [], "ToMigrate": [["api-gateway", "node19-garr-pa1", "node10-garr-ct1"], ["webapp", "node19-garr-pa1", "node10-garr-ct1"], ["invoices_db", "node19-garr-pa1", "node10-garr-ct1"], ["invoices", "node19-garr-pa1", "node10-garr-ct1"], ["products_db", "node19-garr-pa1", "node10-garr-ct1"], ["products", "node19-garr-pa1", "node10-garr-ct1"], ["customers_db", "node19-garr-pa1", "node10-garr-ct1"], ["customers", "node19-garr-pa1", "node10-garr-ct1"]]}, "ToMigrate": 8, "avg-to_migrate": 2.5321507453918457, "actuate": 145.82245755195618, "total_time": 381.9221775531769}, {"cmd": "exec docker-swarm-demo-48", "app": "/home/ubuntu/FogArmX/GARR/apps/docker-swarm-demo-48", "timestamp": 1655713348.440619, "fogbrain": 0.08214068412780762, "Placement": {"application": "docker-swarm-demo-48", "ToAdd": [], "ToRemove": [], "ToMigrate": [["api-gateway", "node19-garr-pa1", "node10-garr-ct1"], ["webapp", "node19-garr-pa1", "node10-garr-ct1"], ["invoices_db", "node19-garr-pa1", "node10-garr-ct1"], ["invoices", "node19-garr-pa1", "node10-garr-ct1"], ["products_db", "node19-garr-pa1", "node10-garr-ct1"], ["products", "node19-garr-pa1", "node10-garr-ct1"], ["customers_db", "node19-garr-pa1", "node10-garr-ct1"], ["customers", "node19-garr-pa1", "node10-garr-ct1"]]}, "ToMigrate": 8, "avg-to_migrate": 2.1986507177352905, "actuate": 138.49832582473755, "total_time": 403.15180349349976}, {"cmd": "exec docker-swarm-demo-49", "app": "/home/ubuntu/FogArmX/GARR/apps/docker-swarm-demo-49", "timestamp": 1655713847.3117645, "fogbrain": 0.08934497833251953, "Placement": {"application": "docker-swarm-demo-49", "ToAdd": [], "ToRemove": [], "ToMigrate": [["api-gateway", "node19-garr-pa1", "node10-garr-ct1"], ["webapp", "node19-garr-pa1", "node10-garr-ct1"], ["invoices_db", "node19-garr-pa1", "node10-garr-ct1"], ["invoices", "node19-garr-pa1", "node10-garr-ct1"], ["products_db", "node19-garr-pa1", "node10-garr-ct1"], ["products", "node19-garr-pa1", "node10-garr-ct1"], ["customers_db", "node19-garr-pa1", "node10-garr-ct1"], ["customers", "node19-garr-pa1", "node10-garr-ct1"]]}, "ToMigrate": 8, "avg-to_migrate": 2.1569778323173523, "actuate": 139.9624879360199, "total_time": 390.71538639068604}, {"cmd": "exec docker-swarm-demo-1", "app": "/home/ubuntu/FogArmX/GARR/apps/docker-swarm-demo-1", "timestamp": 1655714318.0102336, "fogbrain": 0.0899055004119873, "Placement": {"application": "docker-swarm-demo-1", "ToAdd": [["api-gateway", "node10-garr-ct1"], ["products", "node10-garr-ct1"]], "ToRemove": [], "ToMigrate": [["webapp", "node19-garr-pa1", "node10-garr-ct1"], ["invoices_db", "node19-garr-pa1", "node10-garr-ct1"], ["invoices", "node19-garr-pa1", "node10-garr-ct1"], ["products_db", "node19-garr-pa1", "node10-garr-ct1"], ["customers_db", "node19-garr-pa1", "node10-garr-ct1"], ["customers", "node19-garr-pa1", "node10-garr-ct1"]]}, "ToAdd": 2, "avg-to_add": 60.77014708518982, "ToMigrate": 6, "avg-to_migrate": 2.8901331424713135, "actuate": 225.28861927986145, "total_time": 450.28192591667175}]